alegra/__init__.py
alegra/actions.py
alegra/contacts.py
alegra/invoices.py
alegra/items.py
alegra/payments.py
alegra/session.py
alegrapy-0.0.3.dist-info/licenses/LICENSE.txt
alegrapy-0.0.3.dist-info/METADATA
alegrapy-0.0.3.dist-info/WHEEL
alegrapy-0.0.3.dist-info/top_level.txt
alegrapy-0.0.3.dist-info/RECORD
