Metadata-Version: 2.4
Name: AlegraPy
Version: 0.0.3
Summary: Este paquete nos permite consumir el API de Alegra
Home-page: https://github.com/andresroh/alegrapy_package
Author: Camilo Andrés Rodríguez Higuera
Author-email: andres.roh@gmail.com
License: MIT
Keywords: python,alegra,alegra.com
Classifier: Development Status :: 3 - Alpha
Classifier: Intended Audience :: Developers
Classifier: Topic :: Software Development :: Build Tools
Classifier: License :: OSI Approved :: MIT License
Classifier: Programming Language :: Python :: 3
License-File: LICENSE.txt
Requires-Dist: requests
Dynamic: author
Dynamic: author-email
Dynamic: classifier
Dynamic: description
Dynamic: description-content-type
Dynamic: home-page
Dynamic: keywords
Dynamic: license
Dynamic: license-file
Dynamic: requires-dist
Dynamic: summary
